{
  "witness": "W-WP07-PI-ASSETS",
  "expectedCount": 12,
  "skillCount": 6,
  "promptCount": 6,
  "families": [
    "pi-prompt-templates",
    "pi-skill-files"
  ],
  "sha256": [
    {
      "path": ".pi/skills/brainstorm/SKILL.md",
      "familyId": "pi-skill-files",
      "kind": "skill",
      "sha256": "sha256:49bf07ad98e38bfc30c8ef799496e831eebca88ceaa9415416f66de214d74366"
    },
    {
      "path": ".pi/skills/grill-me/SKILL.md",
      "familyId": "pi-skill-files",
      "kind": "skill",
      "sha256": "sha256:5833ed5be328dcf82ccca1eee81bc5549d57fe6580b94f5c204d66de71909284"
    },
    {
      "path": ".pi/skills/task/SKILL.md",
      "familyId": "pi-skill-files",
      "kind": "skill",
      "sha256": "sha256:9f0da89dc1c582fc8dd4203addac3f06fa7ec318f0748d90ec2b709469074c07"
    },
    {
      "path": ".pi/skills/plan/SKILL.md",
      "familyId": "pi-skill-files",
      "kind": "skill",
      "sha256": "sha256:c343a55d73d5ac303416f0756f58344b89e9986754b7860247fc043c498b1e12"
    },
    {
      "path": ".pi/skills/build/SKILL.md",
      "familyId": "pi-skill-files",
      "kind": "skill",
      "sha256": "sha256:a7f10416ae124181dbe737eca337306adc6e08a2295e19f0b799902174bdd726"
    },
    {
      "path": ".pi/skills/ship/SKILL.md",
      "familyId": "pi-skill-files",
      "kind": "skill",
      "sha256": "sha256:53487f53b880d27ae05e8d619abe7eaa7285e219cbfc53e7a01ec7108d035689"
    },
    {
      "path": ".pi/prompts/vibe-brainstorm.md",
      "familyId": "pi-prompt-templates",
      "kind": "prompt-template",
      "sha256": "sha256:306e78e1b2c809a46834e7b3c22398bc0aa0331a63e86e4852eacaf76be819c5"
    },
    {
      "path": ".pi/prompts/vibe-grill-me.md",
      "familyId": "pi-prompt-templates",
      "kind": "prompt-template",
      "sha256": "sha256:5557b07826ba7ff688a5b02ea2343f0e586fa8e7a8bd66d37ef9e4fa9372bc38"
    },
    {
      "path": ".pi/prompts/vibe-task.md",
      "familyId": "pi-prompt-templates",
      "kind": "prompt-template",
      "sha256": "sha256:f55933c414cf1c0c27593be308dbc6f4c0e7f2077a78d0fca937ef99c39ec11a"
    },
    {
      "path": ".pi/prompts/vibe-plan.md",
      "familyId": "pi-prompt-templates",
      "kind": "prompt-template",
      "sha256": "sha256:9865f7fb00942323a465178dba1d1a2cf736b6f8ad510d6fce465dc298c6465a"
    },
    {
      "path": ".pi/prompts/vibe-build.md",
      "familyId": "pi-prompt-templates",
      "kind": "prompt-template",
      "sha256": "sha256:98666a2a6ed06100962ef7094998cd1e962724647db7638d13257bbb40ea72a5"
    },
    {
      "path": ".pi/prompts/vibe-ship.md",
      "familyId": "pi-prompt-templates",
      "kind": "prompt-template",
      "sha256": "sha256:f44242fddb413c0e0f076a8a337431ec36f2ed17dd4cfe05aa2a48fccf35ef51"
    }
  ]
}
